orqviz/__init__.py
orqviz/aliases.py
orqviz/geometric.py
orqviz/gradients.py
orqviz/io.py
orqviz/loss_function.py
orqviz/plot_utils.py
orqviz/plots.py
orqviz/utils.py
orqviz/elastic_band/__init__.py
orqviz/elastic_band/auto_neb.py
orqviz/elastic_band/data_structures.py
orqviz/elastic_band/neb.py
orqviz/elastic_band/plots.py
orqviz/hessians/__init__.py
orqviz/hessians/data_structures.py
orqviz/hessians/hessians.py
orqviz/hessians/plots.py
orqviz/pca/__init__.py
orqviz/pca/data_structures.py
orqviz/pca/plots.py
orqviz/pca/scans.py
orqviz/scans/__init__.py
orqviz/scans/data_structures.py
orqviz/scans/evals.py
orqviz/scans/plots.py
orqviz/scans/scans_1D.py
orqviz/scans/scans_2D.py
orqviz-0.2.0.dist-info/LICENSE
orqviz-0.2.0.dist-info/METADATA
orqviz-0.2.0.dist-info/WHEEL
orqviz-0.2.0.dist-info/top_level.txt
orqviz-0.2.0.dist-info/RECORD
