Metadata-Version: 2.1
Name: orqviz
Version: 0.2.0
Summary: Python package for visualizing the loss landscapes of Variational Quantum Algorithms
Home-page: https://github.com/zapatacomputing/orqviz
Author: Zapata Computing Inc.
Author-email: info@zapatacomputing.com,
License: Apache Software License
Platform: UNKNOWN
Classifier: Programming Language :: Python :: 3.7
Classifier: Operating System :: OS Independent
Classifier: License :: OSI Approved :: Apache Software License
Classifier: Topic :: Scientific/Engineering
Requires-Python: >=3.7
License-File: LICENSE
Requires-Dist: numpy (>=1.14.6)
Requires-Dist: scipy (>=1.5.4)
Requires-Dist: matplotlib (>=2.2.5)
Requires-Dist: scikit-learn (>=1.0)
Provides-Extra: dev
Requires-Dist: pytest (>=3.7.1) ; extra == 'dev'
Requires-Dist: pytest-cov (>=3.0.0) ; extra == 'dev'
Requires-Dist: black (>=20.8b) ; extra == 'dev'
Requires-Dist: flake8 (>=3.9) ; extra == 'dev'
Requires-Dist: mypy (==v0.812) ; extra == 'dev'
Requires-Dist: isort (>=5.8) ; extra == 'dev'
